pyrus_nn/__init__.py
pyrus_nn/_version.py
pyrus_nn/layers.py
pyrus_nn/models.py
pyrus_nn/rust/__init__.py
pyrus_nn/rust/pyrus_nn.cp36-win_amd64.pyd
pyrus_nn-0.2.1.dist-info/METADATA
pyrus_nn-0.2.1.dist-info/RECORD
pyrus_nn-0.2.1.dist-info/WHEEL
pyrus_nn-0.2.1.dist-info/top_level.txt
tests/__init__.py
tests/test_pyrus_sequential.py
